distill/__init__.py
distill/__version__.py
distill/analytics/__init__.py
distill/analytics/graph/README.md
distill/analytics/graph/__init__.py
distill/analytics/graph/conf.py
distill/analytics/graph/graph.py
distill/analytics/stat/__init__.py
distill/analytics/stat/stats.py
distill/process/__init__.py
distill/process/search.py
distill/process/transform.py
distill/segmentation/README.rst
distill/segmentation/__init__.py
distill/segmentation/segment.py
distill/segmentation/segmentation_error.py
distill/segmentation/segments.py
distill/utils/__init__.py
distill/utils/crud.py
flagon_distill-0.1.0.dist-info/LICENSE
flagon_distill-0.1.0.dist-info/METADATA
flagon_distill-0.1.0.dist-info/WHEEL
flagon_distill-0.1.0.dist-info/entry_points.txt
flagon_distill-0.1.0.dist-info/RECORD
