Metadata-Version: 2.1
Name: flagon-distill
Version: 0.1.0
Summary: An analytics framework for front-end UserALE data, enabling modeling, sequence analysis, and customization in Python.
License: Apache-2.0
Requires-Python: >=3.8,<4.0
Classifier: Development Status :: 4 - Beta
Classifier: Environment :: Web Environment
Classifier: Framework :: Flask
Classifier: Intended Audience :: Developers
Classifier: Intended Audience :: Science/Research
Classifier: License :: OSI Approved :: Apache Software License
Classifier: Natural Language :: English
Classifier: Operating System :: OS Independent
Classifier: Programming Language :: Python
Classifier: Programming Language :: Python :: 3
Classifier: Programming Language :: Python :: 3.8
Classifier: Programming Language :: Python :: 3.9
Classifier: Programming Language :: Python :: 3.10
Classifier: Programming Language :: Python :: 3.11
Classifier: Topic :: Internet :: Log Analysis
Requires-Dist: networkx (>=2.5,<3.0)
Requires-Dist: pandas (>=1.2.4,<2.0.0)
Requires-Dist: plotly (>=5.5.0,<6.0.0)
Project-URL: Documentation, http://flagon.incubator.apache.org/distill/
